kdistiller/__init__.py
kdistiller/__main__.py
kdistiller/train.py
knowledge_distiller-0.0.3.dist-info/LICENSE
knowledge_distiller-0.0.3.dist-info/METADATA
knowledge_distiller-0.0.3.dist-info/WHEEL
knowledge_distiller-0.0.3.dist-info/entry_points.txt
knowledge_distiller-0.0.3.dist-info/top_level.txt
knowledge_distiller-0.0.3.dist-info/RECORD
