Metadata-Version: 2.1
Name: knowledge-distiller
Version: 0.0.3
Summary: Distilling knowledge from a ml model
Author-email: Felix Jobson <felix.jobson@outlook.de>
License: MIT License
Requires-Python: >=3.9
License-File: LICENSE
Requires-Dist: numpy ==1.22.4
Provides-Extra: dev
Requires-Dist: pytest ; extra == 'dev'
Requires-Dist: flake8 ; extra == 'dev'
